{"url":"https:\/\/ddtm.bitrix24.vn\/rest\/37552\/ffio7v4s9hae8sgv\/crm.product.list.json","info":{"url":"https:\/\/ddtm.bitrix24.vn\/rest\/37552\/ffio7v4s9hae8sgv\/crm.product.list.json","content_type":"application\/json; charset=utf-8","http_code":200,"header_size":1097,"request_size":209,"filetime":-1,"ssl_verify_result":0,"redirect_count":0,"total_time":0.469577,"namelookup_time":0.026374,"connect_time":0.060853,"pretransfer_time":0.140759,"size_upload":25,"size_download":839,"speed_download":1788,"speed_upload":53,"download_content_length":-1,"upload_content_length":25,"starttransfer_time":0.140807,"redirect_time":0,"redirect_url":"","primary_ip":"18.140.166.245","certinfo":[],"primary_port":443,"local_ip":"103.226.249.222","local_port":55050,"http_version":3,"protocol":2,"ssl_verifyresult":0,"scheme":"HTTPS","appconnect_time_us":140515,"connect_time_us":60853,"namelookup_time_us":26374,"pretransfer_time_us":140759,"redirect_time_us":0,"starttransfer_time_us":140807,"total_time_us":469577},"params":{"method":"crm.product.list","params":{"filter":{"XML_ID":"100275"}}},"result":{"result":[{"ID":"1158","NAME":"Pin S\u1ea1c d\u1ef1 ph\u00f2ng (Wireless) Samsung 10000mAh EB-U1200 Ch\u00ednh h\u00e3ng","CODE":"pin_s_c_d_ph_ng_wireless_samsung_10000mah_eb_u1200_ch_nh_h_ng","ACTIVE":"Y","PREVIEW_PICTURE":null,"DETAIL_PICTURE":null,"SORT":"500","XML_ID":"100275","TIMESTAMP_X":"2022-02-15T13:07:08+03:00","DATE_CREATE":"2022-02-15T13:07:08+03:00","MODIFIED_BY":"1","CREATED_BY":"1","CATALOG_ID":"24","SECTION_ID":"162","DESCRIPTION":null,"DESCRIPTION_TYPE":"text","PRICE":"790.00","CURRENCY_ID":"VND","VAT_ID":null,"VAT_INCLUDED":"N","MEASURE":null}],"total":1,"time":{"start":1659930102.446621,"finish":1659930102.509034,"duration":0.06241297721862793,"processing":0.03795504570007324,"date_start":"2022-08-08T06:41:42+03:00","date_finish":"2022-08-08T06:41:42+03:00","operating_reset_at":1659930702,"operating":0}}}