{"url":"https:\/\/ddtm.bitrix24.vn\/rest\/1\/ybwzqvh1n5n8qld0\/crm.deal.update.json","info":{"url":"https:\/\/ddtm.bitrix24.vn\/rest\/1\/ybwzqvh1n5n8qld0\/crm.deal.update.json","content_type":"application\/json; charset=utf-8","http_code":200,"header_size":1098,"request_size":205,"filetime":-1,"ssl_verify_result":0,"redirect_count":0,"total_time":0.736959,"namelookup_time":0.06709,"connect_time":0.130417,"pretransfer_time":0.272314,"size_upload":388,"size_download":272,"speed_download":369,"speed_upload":527,"download_content_length":-1,"upload_content_length":388,"starttransfer_time":0.272387,"redirect_time":0,"redirect_url":"","primary_ip":"18.140.166.245","certinfo":[],"primary_port":443,"local_ip":"103.226.249.222","local_port":56718,"http_version":3,"protocol":2,"ssl_verifyresult":0,"scheme":"HTTPS","appconnect_time_us":271909,"connect_time_us":130417,"namelookup_time_us":67090,"pretransfer_time_us":272314,"redirect_time_us":0,"starttransfer_time_us":272387,"total_time_us":736959},"params":{"method":"crm.deal.update","params":{"id":"32160","fields":{"COMMENTS":"\r\n- Lo\u1ea1i: \u0110\u01a1n h\u00e0ng.\r\n- Lo\u1ea1i thanh to\u00e1n: Chuy\u1ec3n kho\u1ea3n ng\u00e2n h\u00e0ng.\r\n- Ghi ch\u00fa: Xu\u1ea5t h\u00f3a \u0111\u01a1n cho C\u00f4ng ty TNHH Th\u00e1ch Th\u1ee9c S\u00e1ng t\u1ea1o MBI, MST 0108150120.\r\n-  -  - SL  |  -  - SL  |  -  - SL \r\n                    "}}},"result":{"result":true,"time":{"start":1664751621.287089,"finish":1664751621.455495,"duration":0.16840600967407227,"processing":0.14388108253479004,"date_start":"2022-10-03T02:00:21+03:00","date_finish":"2022-10-03T02:00:21+03:00","operating_reset_at":1664752221,"operating":0}}}