{"url":"https:\/\/ddtm.bitrix24.vn\/rest\/37552\/ffio7v4s9hae8sgv\/crm.contact.update.json","info":{"url":"https:\/\/ddtm.bitrix24.vn\/rest\/37552\/ffio7v4s9hae8sgv\/crm.contact.update.json","content_type":"application\/json; charset=utf-8","http_code":200,"header_size":1097,"request_size":212,"filetime":-1,"ssl_verify_result":0,"redirect_count":0,"total_time":0.568105,"namelookup_time":0.047864,"connect_time":0.084603,"pretransfer_time":0.167822,"size_upload":352,"size_download":239,"speed_download":420,"speed_upload":619,"download_content_length":-1,"upload_content_length":352,"starttransfer_time":0.167866,"redirect_time":0,"redirect_url":"","primary_ip":"18.140.166.245","certinfo":[],"primary_port":443,"local_ip":"103.226.249.222","local_port":40878},"params":{"method":"crm.contact.update","params":{"id":"64786","fields":{"NAME":"T\u1ea1 \u0110\u0103ng M\u1ea1nh","ADDRESS":"Th\u00f4n gia ph\u00fa -x\u00e3 b\u00ecnh d\u01b0\u01a1ng -huy\u1ec7n gia b\u00ecnh -t\u1ec9nh b\u1eafc ninh","ADDRESS_COUNTRY":"Vi\u1ec7t Nam","EMAIL":[{"VALUE":"Baohan3025@gmail.com","VALUE_TYPE":"WORK"}]}}},"result":{"result":true,"time":{"start":1657517298.808445,"finish":1657517298.943968,"duration":0.13552308082580566,"processing":0.11282515525817871,"date_start":"2022-07-11T08:28:18+03:00","date_finish":"2022-07-11T08:28:18+03:00","operating":0}}}