{"url":"https:\/\/ddtm.bitrix24.vn\/rest\/1\/ybwzqvh1n5n8qld0\/crm.contact.list.json","info":{"url":"https:\/\/ddtm.bitrix24.vn\/rest\/1\/ybwzqvh1n5n8qld0\/crm.contact.list.json","content_type":"application\/json; charset=utf-8","http_code":200,"header_size":1099,"request_size":206,"filetime":-1,"ssl_verify_result":0,"redirect_count":0,"total_time":0.633351,"namelookup_time":0.078985,"connect_time":0.146836,"pretransfer_time":0.293897,"size_upload":352,"size_download":280,"speed_download":442,"speed_upload":556,"download_content_length":-1,"upload_content_length":352,"starttransfer_time":0.293964,"redirect_time":0,"redirect_url":"","primary_ip":"18.140.166.245","certinfo":[],"primary_port":443,"local_ip":"103.226.249.222","local_port":35966,"http_version":3,"protocol":2,"ssl_verifyresult":0,"scheme":"HTTPS","appconnect_time_us":293604,"connect_time_us":146836,"namelookup_time_us":78985,"pretransfer_time_us":293897,"redirect_time_us":0,"starttransfer_time_us":293964,"total_time_us":633351},"params":{"method":"crm.contact.list","params":{"filter":{"PHONE":"+84938860277"},"select":["ID","NAME","PHONE","EMAIL","ADDRESS","ADDRESS_CITY","ADDRESS_REGION","ADDRESS_PROVINCE","ADDRESS_COUNTRY","TYPE_ID","SOURCE_ID","ASSIGNED_BY_ID","MODIFY_BY_ID"]}},"result":{"result":[],"total":0,"time":{"start":1664376187.096824,"finish":1664376187.14275,"duration":0.04592609405517578,"processing":0.025998830795288086,"date_start":"2022-09-28T17:43:07+03:00","date_finish":"2022-09-28T17:43:07+03:00","operating_reset_at":1664376787,"operating":0}}}