{"url":"https:\/\/ddtm.bitrix24.vn\/rest\/37552\/ffio7v4s9hae8sgv\/crm.contact.add.json","info":{"url":"https:\/\/ddtm.bitrix24.vn\/rest\/37552\/ffio7v4s9hae8sgv\/crm.contact.add.json","content_type":"application\/json; charset=utf-8","http_code":200,"header_size":1096,"request_size":209,"filetime":-1,"ssl_verify_result":0,"redirect_count":0,"total_time":0.679139,"namelookup_time":0.047577,"connect_time":0.092817,"pretransfer_time":0.19481,"size_upload":687,"size_download":272,"speed_download":400,"speed_upload":1011,"download_content_length":-1,"upload_content_length":687,"starttransfer_time":0.194891,"redirect_time":0,"redirect_url":"","primary_ip":"18.140.166.245","certinfo":[],"primary_port":443,"local_ip":"103.226.249.222","local_port":34286,"http_version":3,"protocol":2,"ssl_verifyresult":0,"scheme":"HTTPS","appconnect_time_us":194491,"connect_time_us":92817,"namelookup_time_us":47577,"pretransfer_time_us":194810,"redirect_time_us":0,"starttransfer_time_us":194891,"total_time_us":679139},"params":{"method":"crm.contact.add","params":{"fields":{"NAME":"Nguy\u1ec5n Quang R\u00f4n","OPENED":"Y","ASSIGNED_BY_ID":1,"TYPE_ID":"CLIENT","SOURCE_ID":"SELF","PHONE":[{"VALUE":"0934777645","VALUE_TYPE":"WORK"}],"EMAIL":[{"VALUE":"ddtmonline@gmail.com","VALUE_TYPE":"WORK"}],"ADDRESS":"5\/73 L\u00ea Trung \u0110\u00ecnh, Thu\u1eadn L\u1ed9c, Hu\u1ebf, Th\u1eeba Thi\u00ean Hu\u1ebf","ADDRESS_CITY":"Hu\u1ebf","ADDRESS_REGION":"Thu\u1eadn L\u1ed9c","ADDRESS_PROVINCE":"Th\u1eeba Thi\u00ean Hu\u1ebf","ADDRESS_COUNTRY":"Vi\u1ec7t Nam"}}},"result":{"result":66858,"time":{"start":1659844123.602864,"finish":1659844123.812095,"duration":0.20923089981079102,"processing":0.18874502182006836,"date_start":"2022-08-07T06:48:43+03:00","date_finish":"2022-08-07T06:48:43+03:00","operating_reset_at":1659844723,"operating":0}}}