{"url":"https:\/\/ddtm.bitrix24.vn\/rest\/8\/yx6uciy52slgpl0n\/crm.contact.add.json","info":{"url":"https:\/\/ddtm.bitrix24.vn\/rest\/8\/yx6uciy52slgpl0n\/crm.contact.add.json","content_type":"application\/json; charset=utf-8","http_code":401,"header_size":691,"request_size":205,"filetime":-1,"ssl_verify_result":0,"redirect_count":0,"total_time":0.561351,"namelookup_time":0.058087,"connect_time":0.11646,"pretransfer_time":0.242312,"size_upload":639,"size_download":81,"speed_download":144,"speed_upload":1139,"download_content_length":-1,"upload_content_length":639,"starttransfer_time":0.242372,"redirect_time":0,"redirect_url":"","primary_ip":"18.140.166.245","certinfo":[],"primary_port":443,"local_ip":"103.226.249.222","local_port":39352,"http_version":3,"protocol":2,"ssl_verifyresult":0,"scheme":"HTTPS","appconnect_time_us":242041,"connect_time_us":116460,"namelookup_time_us":58087,"pretransfer_time_us":242312,"redirect_time_us":0,"starttransfer_time_us":242372,"total_time_us":561351},"params":{"method":"crm.contact.add","params":{"fields":{"NAME":"Mai","OPENED":"Y","ASSIGNED_BY_ID":1,"TYPE_ID":"CLIENT","SOURCE_ID":"SELF","PHONE":[{"VALUE":"0334647905","VALUE_TYPE":"WORK"}],"EMAIL":[{"VALUE":"ddtmonline@gmail.com","VALUE_TYPE":"WORK"}],"ADDRESS":"K6\/5 L\u00ea V\u0103n Th\u1ee9, M\u00e2n Th\u00e1i, S\u01a1n Tr\u00e0, \u0110\u00e0 N\u1eb5ng","ADDRESS_CITY":"S\u01a1n Tr\u00e0","ADDRESS_REGION":"M\u00e2n Th\u00e1i","ADDRESS_PROVINCE":"\u0110\u00e0 N\u1eb5ng","ADDRESS_COUNTRY":"Vi\u1ec7t Nam"}}},"result":{"error":"INVALID_CREDENTIALS","error_description":"Invalid request credentials"}}