{"url":"https:\/\/ddtm.bitrix24.vn\/rest\/37552\/ffio7v4s9hae8sgv\/crm.contact.add.json","info":{"url":"https:\/\/ddtm.bitrix24.vn\/rest\/37552\/ffio7v4s9hae8sgv\/crm.contact.add.json","content_type":"application\/json; charset=utf-8","http_code":200,"header_size":1097,"request_size":209,"filetime":-1,"ssl_verify_result":0,"redirect_count":0,"total_time":0.750664,"namelookup_time":0.035994,"connect_time":0.090917,"pretransfer_time":0.201705,"size_upload":518,"size_download":226,"speed_download":301,"speed_upload":690,"download_content_length":-1,"upload_content_length":518,"starttransfer_time":0.201737,"redirect_time":0,"redirect_url":"","primary_ip":"18.140.166.245","certinfo":[],"primary_port":443,"local_ip":"192.168.0.123","local_port":59430},"params":{"method":"crm.contact.add","params":{"fields":{"NAME":"Hi\u1ebfu \u0110\u1ed3ng","OPENED":"1","ASSIGNED_BY_ID":"1","STAGE_ID":"NEW","TYPE_ID":"CLIENT","SOURCE_ID":"SELF","PHONE":{"VALUE":"0981164763","VALUE_TYPE":"WORK"},"EMAIL":"hieudv@finalstyle.com","ADDRESS":"H\u00e0 N\u1ed9i","ADDRESS_CITY":"H\u00e0 N\u1ed9i","ADDRESS_COUNTRY":"Vi\u1ec7t Nam","ADDRESS_PROVINCE":"H\u00e0 N\u1ed9i","ADDRESS_REGION":"Thanh Tr\u00ec"}}},"result":{"result":6342,"time":{"start":1644892092.4778,"finish":1644892092.708891,"duration":0.23109102249145508,"processing":0.20838117599487305,"date_start":"2022-02-15T05:28:12+03:00","date_finish":"2022-02-15T05:28:12+03:00"}}}