{"url":"https:\/\/ddtm.bitrix24.vn\/rest\/37552\/ffio7v4s9hae8sgv\/crm.contact.update.json","info":{"url":"https:\/\/ddtm.bitrix24.vn\/rest\/37552\/ffio7v4s9hae8sgv\/crm.contact.update.json","content_type":"application\/json; charset=utf-8","http_code":200,"header_size":1097,"request_size":212,"filetime":-1,"ssl_verify_result":0,"redirect_count":0,"total_time":0.70543,"namelookup_time":0.037465,"connect_time":0.079484,"pretransfer_time":0.172374,"size_upload":303,"size_download":258,"speed_download":365,"speed_upload":429,"download_content_length":-1,"upload_content_length":303,"starttransfer_time":0.172428,"redirect_time":0,"redirect_url":"","primary_ip":"18.140.166.245","certinfo":[],"primary_port":443,"local_ip":"103.226.249.222","local_port":60516,"http_version":3,"protocol":2,"ssl_verifyresult":0,"scheme":"HTTPS","appconnect_time_us":172180,"connect_time_us":79484,"namelookup_time_us":37465,"pretransfer_time_us":172374,"redirect_time_us":0,"starttransfer_time_us":172428,"total_time_us":705430},"params":{"method":"crm.contact.update","params":{"id":"65532","fields":{"NAME":"\u0110\u1ed7 nh\u01b0 \u0111\u1ea1t","ADDRESS":"X\u00f3m 7 minh h\u00f2a kinh m\u00f4n h\u1ea3i d\u01b0\u01a1ng","ADDRESS_COUNTRY":"Vi\u1ec7t Nam","EMAIL":[{"VALUE":"dodat1884@gmail.com","VALUE_TYPE":"WORK"}]}}},"result":{"result":true,"time":{"start":1659031155.128935,"finish":1659031155.39576,"duration":0.26682496070861816,"processing":0.24866890907287598,"date_start":"2022-07-28T20:59:15+03:00","date_finish":"2022-07-28T20:59:15+03:00","operating":0.24864983558654785}}}