{"url":"https:\/\/ddtm.bitrix24.vn\/rest\/37552\/ffio7v4s9hae8sgv\/crm.deal.add.json","info":{"url":"https:\/\/ddtm.bitrix24.vn\/rest\/37552\/ffio7v4s9hae8sgv\/crm.deal.add.json","content_type":"application\/json; charset=utf-8","http_code":200,"header_size":1096,"request_size":206,"filetime":-1,"ssl_verify_result":0,"redirect_count":0,"total_time":1.011904,"namelookup_time":0.035016,"connect_time":0.070982,"pretransfer_time":0.154641,"size_upload":718,"size_download":258,"speed_download":255,"speed_upload":710,"download_content_length":-1,"upload_content_length":718,"starttransfer_time":0.154705,"redirect_time":0,"redirect_url":"","primary_ip":"18.140.166.245","certinfo":[],"primary_port":443,"local_ip":"103.226.249.222","local_port":59696,"http_version":3,"protocol":2,"ssl_verifyresult":0,"scheme":"HTTPS","appconnect_time_us":154343,"connect_time_us":70982,"namelookup_time_us":35016,"pretransfer_time_us":154641,"redirect_time_us":0,"starttransfer_time_us":154705,"total_time_us":1011904},"params":{"method":"crm.deal.add","params":{"fields":{"TITLE":"Ph\u00f9ng V\u0103n Tr\u01b0\u1eddng - T\u1eeb Website","STAGE_ID":"C4:NEW","CATEGORY_ID":4,"CURRENCY_ID":"VND","OPPORTUNITY":14990000,"ASSIGNED_BY_ID":"1","CONTACT_ID":"66290","UF_CRM_61DA484985CB2":"5474","UF_CRM_620AF42D903F7":568,"UF_CRM_61ECAD7FC4455":"","UF_CRM_1644995613":778,"UF_CRM_1645066604":860,"COMMENTS":"\r\n- Lo\u1ea1i: \u0110\u01a1n h\u00e0ng.\r\n- Lo\u1ea1i thanh to\u00e1n: Ch\u01b0a ch\u1ecdn thanh to\u00e1n.\r\n- Ghi ch\u00fa: Kh\u00f4ng.\r\n- iPhone 11 Pro Max C\u0169 \u0110\u1eb9p 64G - Midnight Green - SL 1\r\n                    "}}},"result":{"result":29826,"time":{"start":1659189887.856974,"finish":1659189888.42685,"duration":0.5698761940002441,"processing":0.5486180782318115,"date_start":"2022-07-30T17:04:47+03:00","date_finish":"2022-07-30T17:04:48+03:00","operating":1.3610169887542725}}}