{"url":"https:\/\/ddtm.bitrix24.vn\/rest\/1\/ybwzqvh1n5n8qld0\/crm.deal.productrows.set.json","info":{"url":"https:\/\/ddtm.bitrix24.vn\/rest\/1\/ybwzqvh1n5n8qld0\/crm.deal.productrows.set.json","content_type":"application\/json; charset=utf-8","http_code":200,"header_size":1099,"request_size":213,"filetime":-1,"ssl_verify_result":0,"redirect_count":0,"total_time":0.710053,"namelookup_time":0.028323,"connect_time":0.099069,"pretransfer_time":0.254994,"size_upload":67,"size_download":270,"speed_download":380,"speed_upload":94,"download_content_length":-1,"upload_content_length":67,"starttransfer_time":0.255016,"redirect_time":0,"redirect_url":"","primary_ip":"18.140.166.245","certinfo":[],"primary_port":443,"local_ip":"103.226.249.222","local_port":58850,"http_version":3,"protocol":2,"ssl_verifyresult":0,"scheme":"HTTPS","appconnect_time_us":254881,"connect_time_us":99069,"namelookup_time_us":28323,"pretransfer_time_us":254994,"redirect_time_us":0,"starttransfer_time_us":255016,"total_time_us":710053},"params":{"method":"crm.deal.productrows.set","params":{"id":31954,"rows":[{"PRODUCT_ID":null,"PRICE":"7690000","QUANTITY":1}]}},"result":{"result":true,"time":{"start":1664507966.89252,"finish":1664507967.043136,"duration":0.15061593055725098,"processing":0.12914800643920898,"date_start":"2022-09-30T06:19:26+03:00","date_finish":"2022-09-30T06:19:27+03:00","operating_reset_at":1664508566,"operating":0}}}