{"url":"https:\/\/ddtm.bitrix24.vn\/rest\/1\/ybwzqvh1n5n8qld0\/crm.contact.add.json","info":{"url":"https:\/\/ddtm.bitrix24.vn\/rest\/1\/ybwzqvh1n5n8qld0\/crm.contact.add.json","content_type":"application\/json; charset=utf-8","http_code":200,"header_size":1099,"request_size":205,"filetime":-1,"ssl_verify_result":0,"redirect_count":0,"total_time":0.906864,"namelookup_time":0.075287,"connect_time":0.145799,"pretransfer_time":0.296619,"size_upload":527,"size_download":271,"speed_download":299,"speed_upload":581,"download_content_length":-1,"upload_content_length":527,"starttransfer_time":0.296683,"redirect_time":0,"redirect_url":"","primary_ip":"18.140.166.245","certinfo":[],"primary_port":443,"local_ip":"103.226.249.222","local_port":46898,"http_version":3,"protocol":2,"ssl_verifyresult":0,"scheme":"HTTPS","appconnect_time_us":296461,"connect_time_us":145799,"namelookup_time_us":75287,"pretransfer_time_us":296619,"redirect_time_us":0,"starttransfer_time_us":296683,"total_time_us":906864},"params":{"method":"crm.contact.add","params":{"fields":{"NAME":"Phong","OPENED":"Y","ASSIGNED_BY_ID":1,"TYPE_ID":"CLIENT","SOURCE_ID":"SELF","PHONE":[{"VALUE":"0965913580","VALUE_TYPE":"WORK"}],"EMAIL":[{"VALUE":"ddtmonline@gmail.com","VALUE_TYPE":"WORK"}],"ADDRESS":"16","ADDRESS_CITY":" P.10","ADDRESS_REGION":"701 L\u00ea H\u1ed3ng Phong","ADDRESS_PROVINCE":" Qu\u1eadn 10","ADDRESS_COUNTRY":"Vi\u1ec7t Nam"}}},"result":{"result":68566,"time":{"start":1663738159.343157,"finish":1663738159.652925,"duration":0.3097679615020752,"processing":0.2832369804382324,"date_start":"2022-09-21T08:29:19+03:00","date_finish":"2022-09-21T08:29:19+03:00","operating_reset_at":1663738759,"operating":0}}}