{"url":"https:\/\/ddtm.bitrix24.vn\/rest\/37552\/ffio7v4s9hae8sgv\/crm.deal.productrows.set.json","info":{"url":"https:\/\/ddtm.bitrix24.vn\/rest\/37552\/ffio7v4s9hae8sgv\/crm.deal.productrows.set.json","content_type":"application\/json; charset=utf-8","http_code":200,"header_size":1097,"request_size":217,"filetime":-1,"ssl_verify_result":0,"redirect_count":0,"total_time":0.594005,"namelookup_time":0.05979,"connect_time":0.097153,"pretransfer_time":0.177961,"size_upload":68,"size_download":254,"speed_download":427,"speed_upload":114,"download_content_length":-1,"upload_content_length":68,"starttransfer_time":0.177984,"redirect_time":0,"redirect_url":"","primary_ip":"18.140.166.245","certinfo":[],"primary_port":443,"local_ip":"103.226.249.222","local_port":36390},"params":{"method":"crm.deal.productrows.set","params":{"id":27776,"rows":[{"PRODUCT_ID":null,"PRICE":"24390000","QUANTITY":1}]}},"result":{"result":true,"time":{"start":1656912375.5265,"finish":1656912375.671224,"duration":0.14472413063049316,"processing":0.12210798263549805,"date_start":"2022-07-04T08:26:15+03:00","date_finish":"2022-07-04T08:26:15+03:00","operating":1.3271191120147705}}}