{"url":"https:\/\/ddtm.bitrix24.vn\/rest\/37552\/ffio7v4s9hae8sgv\/crm.product.list.json","info":{"url":"https:\/\/ddtm.bitrix24.vn\/rest\/37552\/ffio7v4s9hae8sgv\/crm.product.list.json","content_type":"application\/json; charset=utf-8","http_code":200,"header_size":1096,"request_size":209,"filetime":-1,"ssl_verify_result":0,"redirect_count":0,"total_time":0.526024,"namelookup_time":0.053057,"connect_time":0.098028,"pretransfer_time":0.197734,"size_upload":33,"size_download":249,"speed_download":473,"speed_upload":62,"download_content_length":-1,"upload_content_length":33,"starttransfer_time":0.197774,"redirect_time":0,"redirect_url":"","primary_ip":"18.140.166.245","certinfo":[],"primary_port":443,"local_ip":"103.226.249.222","local_port":38962},"params":{"method":"crm.product.list","params":{"filter":{"XML_ID":"SM-A235FLBGXXV"}}},"result":{"result":[],"total":0,"time":{"start":1656575717.255073,"finish":1656575717.310205,"duration":0.05513191223144531,"processing":0.03652787208557129,"date_start":"2022-06-30T10:55:17+03:00","date_finish":"2022-06-30T10:55:17+03:00","operating":0}}}