{"url":"https:\/\/ddtm.bitrix24.vn\/rest\/37552\/ffio7v4s9hae8sgv\/crm.contact.list.json","info":{"url":"https:\/\/ddtm.bitrix24.vn\/rest\/37552\/ffio7v4s9hae8sgv\/crm.contact.list.json","content_type":"application\/json; charset=utf-8","http_code":200,"header_size":1097,"request_size":210,"filetime":-1,"ssl_verify_result":0,"redirect_count":0,"total_time":0.69743,"namelookup_time":0.035482,"connect_time":0.084441,"pretransfer_time":0.195673,"size_upload":352,"size_download":248,"speed_download":355,"speed_upload":505,"download_content_length":-1,"upload_content_length":352,"starttransfer_time":0.195711,"redirect_time":0,"redirect_url":"","primary_ip":"18.140.166.245","certinfo":[],"primary_port":443,"local_ip":"103.226.249.222","local_port":45162},"params":{"method":"crm.contact.list","params":{"filter":{"PHONE":"+84793777728"},"select":["ID","NAME","PHONE","EMAIL","ADDRESS","ADDRESS_CITY","ADDRESS_REGION","ADDRESS_PROVINCE","ADDRESS_COUNTRY","TYPE_ID","SOURCE_ID","ASSIGNED_BY_ID","MODIFY_BY_ID"]}},"result":{"result":[],"total":0,"time":{"start":1655729038.373218,"finish":1655729038.568214,"duration":0.19499588012695312,"processing":0.13708281517028809,"date_start":"2022-06-20T15:43:58+03:00","date_finish":"2022-06-20T15:43:58+03:00","operating":0}}}