{"url":"https:\/\/ddtm.bitrix24.vn\/rest\/1\/ybwzqvh1n5n8qld0\/crm.product.list.json","info":{"url":"https:\/\/ddtm.bitrix24.vn\/rest\/1\/ybwzqvh1n5n8qld0\/crm.product.list.json","content_type":"application\/json; charset=utf-8","http_code":200,"header_size":1099,"request_size":205,"filetime":-1,"ssl_verify_result":0,"redirect_count":0,"total_time":0.670962,"namelookup_time":0.061365,"connect_time":0.13113,"pretransfer_time":0.281862,"size_upload":27,"size_download":740,"speed_download":1104,"speed_upload":40,"download_content_length":-1,"upload_content_length":27,"starttransfer_time":0.281905,"redirect_time":0,"redirect_url":"","primary_ip":"18.140.166.245","certinfo":[],"primary_port":443,"local_ip":"103.226.249.222","local_port":47818,"http_version":3,"protocol":2,"ssl_verifyresult":0,"scheme":"HTTPS","appconnect_time_us":281663,"connect_time_us":131130,"namelookup_time_us":61365,"pretransfer_time_us":281862,"redirect_time_us":0,"starttransfer_time_us":281905,"total_time_us":670962},"params":{"method":"crm.product.list","params":{"filter":{"XML_ID":"IP864DOQ"}}},"result":{"result":[{"ID":"6476","NAME":"IPHONE 8 64GB \u0110O\u0309 C\u0168","CODE":"iphone_8_64gb_o_c","ACTIVE":"Y","PREVIEW_PICTURE":null,"DETAIL_PICTURE":null,"SORT":"500","XML_ID":"IP864DOQ","TIMESTAMP_X":"2022-02-15T13:08:39+03:00","DATE_CREATE":"2022-02-15T13:08:39+03:00","MODIFIED_BY":"1","CREATED_BY":"1","CATALOG_ID":"24","SECTION_ID":"162","DESCRIPTION":null,"DESCRIPTION_TYPE":"text","PRICE":"4.79","CURRENCY_ID":"VND","VAT_ID":null,"VAT_INCLUDED":"N","MEASURE":null}],"total":1,"time":{"start":1665075639.751087,"finish":1665075639.838218,"duration":0.08713102340698242,"processing":0.04815411567687988,"date_start":"2022-10-06T20:00:39+03:00","date_finish":"2022-10-06T20:00:39+03:00","operating_reset_at":1665076239,"operating":0}}}