{"url":"https:\/\/ddtm.bitrix24.vn\/rest\/1\/ybwzqvh1n5n8qld0\/crm.deal.add.json","info":{"url":"https:\/\/ddtm.bitrix24.vn\/rest\/1\/ybwzqvh1n5n8qld0\/crm.deal.add.json","content_type":"application\/json; charset=utf-8","http_code":200,"header_size":1099,"request_size":202,"filetime":-1,"ssl_verify_result":0,"redirect_count":0,"total_time":1.346589,"namelookup_time":0.05914,"connect_time":0.129691,"pretransfer_time":0.282191,"size_upload":725,"size_download":289,"speed_download":214,"speed_upload":538,"download_content_length":-1,"upload_content_length":725,"starttransfer_time":0.282255,"redirect_time":0,"redirect_url":"","primary_ip":"18.140.166.245","certinfo":[],"primary_port":443,"local_ip":"103.226.249.222","local_port":46840,"http_version":3,"protocol":2,"ssl_verifyresult":0,"scheme":"HTTPS","appconnect_time_us":281933,"connect_time_us":129691,"namelookup_time_us":59140,"pretransfer_time_us":282191,"redirect_time_us":0,"starttransfer_time_us":282255,"total_time_us":1346589},"params":{"method":"crm.deal.add","params":{"fields":{"TITLE":"l\u00ea nh\u01b0 tu\u1ea5n - T\u1eeb Website","STAGE_ID":"C4:NEW","CATEGORY_ID":4,"CURRENCY_ID":"VND","OPPORTUNITY":"24990000","ASSIGNED_BY_ID":1,"CONTACT_ID":69110,"UF_CRM_61DA484985CB2":"13593","UF_CRM_620AF42D903F7":570,"UF_CRM_61ECAD7FC4455":"","UF_CRM_1644995613":778,"UF_CRM_1645066604":862,"COMMENTS":"\r\n- Lo\u1ea1i: Tr\u1ea3 g\u00f3p - Tr\u1ea3 g\u00f3p qua th\u1ebb t\u00edn d\u1ee5ng.\r\n- Ghi ch\u00fa: \u0027\u0027\r\n- iPhone 13 Pro 256GB Ch\u00ednh h\u00e3ng VN\/A - Tr\u1ea3 b\u1ea3o h\u00e0nh - V\u00e0ng - 24.990.000 VND\r\n                    "}}},"result":{"result":31786,"time":{"start":1664332517.057452,"finish":1664332517.817806,"duration":0.7603540420532227,"processing":0.735713005065918,"date_start":"2022-09-28T05:35:17+03:00","date_finish":"2022-09-28T05:35:17+03:00","operating_reset_at":1664333117,"operating":0.7356967926025391}}}