{"url":"https:\/\/ddtm.bitrix24.vn\/rest\/37552\/ffio7v4s9hae8sgv\/crm.deal.add.json","info":{"url":"https:\/\/ddtm.bitrix24.vn\/rest\/37552\/ffio7v4s9hae8sgv\/crm.deal.add.json","content_type":"application\/json; charset=utf-8","http_code":200,"header_size":1096,"request_size":207,"filetime":-1,"ssl_verify_result":0,"redirect_count":0,"total_time":2.195895,"namelookup_time":0.033155,"connect_time":0.089677,"pretransfer_time":1.372264,"size_upload":1284,"size_download":258,"speed_download":117,"speed_upload":584,"download_content_length":-1,"upload_content_length":1284,"starttransfer_time":1.372384,"redirect_time":0,"redirect_url":"","primary_ip":"18.140.166.245","certinfo":[],"primary_port":443,"local_ip":"103.226.249.222","local_port":60536,"http_version":3,"protocol":2,"ssl_verifyresult":0,"scheme":"HTTPS","appconnect_time_us":1372138,"connect_time_us":89677,"namelookup_time_us":33155,"pretransfer_time_us":1372264,"redirect_time_us":0,"starttransfer_time_us":1372384,"total_time_us":2195895},"params":{"method":"crm.deal.add","params":{"fields":{"TITLE":"Nguy\u1ec5n Th\u1ecb Chuy\u1ec3n - T\u1eeb Website","STAGE_ID":"C4:NEW","CATEGORY_ID":4,"CURRENCY_ID":"VND","OPPORTUNITY":3390000,"ASSIGNED_BY_ID":1,"CONTACT_ID":66068,"UF_CRM_61DA484985CB2":"5432","UF_CRM_620AF42D903F7":568,"UF_CRM_61ECAD7FC4455":"","UF_CRM_1644995613":778,"UF_CRM_1645066604":860,"COMMENTS":"\r\n- Lo\u1ea1i: \u0110\u01a1n h\u00e0ng.\r\n- Lo\u1ea1i thanh to\u00e1n: Ch\u01b0a ch\u1ecdn thanh to\u00e1n.\r\n- Ghi ch\u00fa: Note : vi\u1ebft h\u00f3a \u0111\u01a1n \u0111\u1ecf theo \u0111\u1ecba ch\u1ec9 cty : C\u00d4NG TY TNHH TH\u01af\u01a0NG M\u1ea0I D\u1ecaCH V\u1ee4 K\u1ef8 THU\u1eacT NAM TH\u00c0NH PH\u00c1T S\u1ed1 261\/15\/78\/5K \u0110\u00ecnh Phong Ph\u00fa, Ph\u01b0\u1eddng T\u0103ng Nh\u01a1n Ph\u00fa B, Th\u00e0nh ph\u1ed1 Th\u1ee7 \u0110\u1ee9c, Th\u00e0nh ph\u1ed1 H\u1ed3 Ch\u00ed Minh, Vi\u1ec7t Nam ; m\u00e3 s\u1ed1 thu\u1ebf :0316407401 .Giao trong gi\u1edd h\u00e0nh ch\u00ednh 8h \u0111\u1ebfn 16h30.\r\n- Xiaomi Redmi 10 4GB\/64GB Ch\u00ednh H\u00e3ng - Xanh - SL 1\r\n                    "}}},"result":{"result":29504,"time":{"start":1658888865.834226,"finish":1658888866.362948,"duration":0.5287220478057861,"processing":0.5000350475311279,"date_start":"2022-07-27T05:27:45+03:00","date_finish":"2022-07-27T05:27:46+03:00","operating":2.0569350719451904}}}