{"url":"https:\/\/ddtm.bitrix24.vn\/rest\/37552\/ffio7v4s9hae8sgv\/crm.contact.update.json","info":{"url":"https:\/\/ddtm.bitrix24.vn\/rest\/37552\/ffio7v4s9hae8sgv\/crm.contact.update.json","content_type":"application\/json; charset=utf-8","http_code":200,"header_size":1097,"request_size":212,"filetime":-1,"ssl_verify_result":0,"redirect_count":0,"total_time":0.641428,"namelookup_time":0.09301,"connect_time":0.135187,"pretransfer_time":0.229768,"size_upload":466,"size_download":238,"speed_download":371,"speed_upload":726,"download_content_length":-1,"upload_content_length":466,"starttransfer_time":0.229795,"redirect_time":0,"redirect_url":"","primary_ip":"18.140.166.245","certinfo":[],"primary_port":443,"local_ip":"103.226.249.222","local_port":55040},"params":{"method":"crm.contact.update","params":{"id":"64192","fields":{"NAME":"N\u00f4ng V\u0103n S\u01a1n","ADDRESS":"S\u1ed1 76 \u0111\u01b0\u1eddng ho\u00e0ng hoa th\u00e1m, B\u1ebfn Th\u00e0nh, Qu\u1eadn 1, TP HCM","ADDRESS_CITY":"Qu\u1eadn 1","ADDRESS_REGION":"B\u1ebfn Th\u00e0nh","ADDRESS_PROVINCE":"TP HCM","ADDRESS_COUNTRY":"Vi\u1ec7t Nam","EMAIL":[{"VALUE":"ddtmonline@gmail.com","VALUE_TYPE":"WORK"}]}}},"result":{"result":true,"time":{"start":1656738889.621372,"finish":1656738889.760543,"duration":0.13917112350463867,"processing":0.1204841136932373,"date_start":"2022-07-02T08:14:49+03:00","date_finish":"2022-07-02T08:14:49+03:00","operating":0}}}