{"url":"https:\/\/ddtm.bitrix24.vn\/rest\/1\/ybwzqvh1n5n8qld0\/crm.product.list.json","info":{"url":"https:\/\/ddtm.bitrix24.vn\/rest\/1\/ybwzqvh1n5n8qld0\/crm.product.list.json","content_type":"application\/json; charset=utf-8","http_code":200,"header_size":1099,"request_size":205,"filetime":-1,"ssl_verify_result":0,"redirect_count":0,"total_time":0.574507,"namelookup_time":0.024496,"connect_time":0.081994,"pretransfer_time":0.207193,"size_upload":25,"size_download":282,"speed_download":491,"speed_upload":43,"download_content_length":-1,"upload_content_length":25,"starttransfer_time":0.207241,"redirect_time":0,"redirect_url":"","primary_ip":"18.140.166.245","certinfo":[],"primary_port":443,"local_ip":"103.226.249.222","local_port":35774,"http_version":3,"protocol":2,"ssl_verifyresult":0,"scheme":"HTTPS","appconnect_time_us":206936,"connect_time_us":81994,"namelookup_time_us":24496,"pretransfer_time_us":207193,"redirect_time_us":0,"starttransfer_time_us":207241,"total_time_us":574507},"params":{"method":"crm.product.list","params":{"filter":{"XML_ID":"W10703"}}},"result":{"result":[],"total":0,"time":{"start":1664464909.608553,"finish":1664464909.68992,"duration":0.08136701583862305,"processing":0.055665016174316406,"date_start":"2022-09-29T18:21:49+03:00","date_finish":"2022-09-29T18:21:49+03:00","operating_reset_at":1664465509,"operating":0}}}