{"url":"https:\/\/ddtm.bitrix24.vn\/rest\/1\/ybwzqvh1n5n8qld0\/crm.contact.add.json","info":{"url":"https:\/\/ddtm.bitrix24.vn\/rest\/1\/ybwzqvh1n5n8qld0\/crm.contact.add.json","content_type":"application\/json; charset=utf-8","http_code":200,"header_size":1099,"request_size":205,"filetime":-1,"ssl_verify_result":0,"redirect_count":0,"total_time":0.968473,"namelookup_time":0.027746,"connect_time":0.085838,"pretransfer_time":0.211229,"size_upload":525,"size_download":273,"speed_download":282,"speed_upload":542,"download_content_length":-1,"upload_content_length":525,"starttransfer_time":0.211278,"redirect_time":0,"redirect_url":"","primary_ip":"18.140.166.245","certinfo":[],"primary_port":443,"local_ip":"103.226.249.222","local_port":56284,"http_version":3,"protocol":2,"ssl_verifyresult":0,"scheme":"HTTPS","appconnect_time_us":211016,"connect_time_us":85838,"namelookup_time_us":27746,"pretransfer_time_us":211229,"redirect_time_us":0,"starttransfer_time_us":211278,"total_time_us":968473},"params":{"method":"crm.contact.add","params":{"fields":{"NAME":"Nguy\u1ec5n Th\u1ebf C\u01b0\u1eddng","OPENED":"Y","ASSIGNED_BY_ID":1,"TYPE_ID":"CLIENT","SOURCE_ID":"SELF","PHONE":[{"VALUE":"0365594495","VALUE_TYPE":"WORK"}],"EMAIL":[{"VALUE":"thecuong.caimon93@gmail.com","VALUE_TYPE":"WORK"}],"ADDRESS":"91\/30 V\u0129nh H\u01b0ng 2 v\u0129nh th\u00e0nh ch\u1ee3 l\u00e1ch b\u1ebfn tre","ADDRESS_COUNTRY":"Vi\u1ec7t Nam"}}},"result":{"result":69238,"time":{"start":1664464605.367669,"finish":1664464605.819255,"duration":0.4515860080718994,"processing":0.41219210624694824,"date_start":"2022-09-29T18:16:45+03:00","date_finish":"2022-09-29T18:16:45+03:00","operating_reset_at":1664465205,"operating":0}}}