{"url":"https:\/\/ddtm.bitrix24.vn\/rest\/1\/ybwzqvh1n5n8qld0\/crm.contact.list.json","info":{"url":"https:\/\/ddtm.bitrix24.vn\/rest\/1\/ybwzqvh1n5n8qld0\/crm.contact.list.json","content_type":"application\/json; charset=utf-8","http_code":200,"header_size":1099,"request_size":206,"filetime":-1,"ssl_verify_result":0,"redirect_count":0,"total_time":1.312656,"namelookup_time":0.057,"connect_time":0.117102,"pretransfer_time":0.247621,"size_upload":351,"size_download":280,"speed_download":213,"speed_upload":267,"download_content_length":-1,"upload_content_length":351,"starttransfer_time":0.247663,"redirect_time":0,"redirect_url":"","primary_ip":"18.140.166.245","certinfo":[],"primary_port":443,"local_ip":"103.226.249.222","local_port":47628,"http_version":3,"protocol":2,"ssl_verifyresult":0,"scheme":"HTTPS","appconnect_time_us":247433,"connect_time_us":117102,"namelookup_time_us":57000,"pretransfer_time_us":247621,"redirect_time_us":0,"starttransfer_time_us":247663,"total_time_us":1312656},"params":{"method":"crm.contact.list","params":{"filter":{"PHONE":"+0965248338"},"select":["ID","NAME","PHONE","EMAIL","ADDRESS","ADDRESS_CITY","ADDRESS_REGION","ADDRESS_PROVINCE","ADDRESS_COUNTRY","TYPE_ID","SOURCE_ID","ASSIGNED_BY_ID","MODIFY_BY_ID"]}},"result":{"result":[],"total":0,"time":{"start":1665102181.368643,"finish":1665102181.499205,"duration":0.13056206703186035,"processing":0.04337501525878906,"date_start":"2022-10-07T03:23:01+03:00","date_finish":"2022-10-07T03:23:01+03:00","operating_reset_at":1665102781,"operating":0}}}