{"url":"https:\/\/ddtm.bitrix24.vn\/rest\/1\/ybwzqvh1n5n8qld0\/crm.contact.add.json","info":{"url":"https:\/\/ddtm.bitrix24.vn\/rest\/1\/ybwzqvh1n5n8qld0\/crm.contact.add.json","content_type":"application\/json; charset=utf-8","http_code":200,"header_size":1099,"request_size":205,"filetime":-1,"ssl_verify_result":0,"redirect_count":0,"total_time":0.798929,"namelookup_time":0.082748,"connect_time":0.148304,"pretransfer_time":0.288665,"size_upload":391,"size_download":272,"speed_download":340,"speed_upload":489,"download_content_length":-1,"upload_content_length":391,"starttransfer_time":0.288708,"redirect_time":0,"redirect_url":"","primary_ip":"18.140.166.245","certinfo":[],"primary_port":443,"local_ip":"103.226.249.222","local_port":43884,"http_version":3,"protocol":2,"ssl_verifyresult":0,"scheme":"HTTPS","appconnect_time_us":288479,"connect_time_us":148304,"namelookup_time_us":82748,"pretransfer_time_us":288665,"redirect_time_us":0,"starttransfer_time_us":288708,"total_time_us":798929},"params":{"method":"crm.contact.add","params":{"fields":{"NAME":"\u0110inh V\u0103n Hi\u1ec7p","OPENED":"Y","ASSIGNED_BY_ID":1,"TYPE_ID":"CLIENT","SOURCE_ID":"SELF","PHONE":[{"VALUE":"0904303333","VALUE_TYPE":"WORK"}],"EMAIL":[{"VALUE":"hiepdv@gmail.com","VALUE_TYPE":"WORK"}],"ADDRESS_COUNTRY":"Vi\u1ec7t Nam"}}},"result":{"result":68370,"time":{"start":1663482895.895272,"finish":1663482896.115646,"duration":0.22037386894226074,"processing":0.19768404960632324,"date_start":"2022-09-18T09:34:55+03:00","date_finish":"2022-09-18T09:34:56+03:00","operating_reset_at":1663483495,"operating":0}}}