{"url":"https:\/\/ddtm.bitrix24.vn\/rest\/37552\/ffio7v4s9hae8sgv\/crm.product.list.json","info":{"url":"https:\/\/ddtm.bitrix24.vn\/rest\/37552\/ffio7v4s9hae8sgv\/crm.product.list.json","content_type":"application\/json; charset=utf-8","http_code":200,"header_size":1097,"request_size":209,"filetime":-1,"ssl_verify_result":0,"redirect_count":0,"total_time":0.504764,"namelookup_time":0.019297,"connect_time":0.07052,"pretransfer_time":0.183332,"size_upload":33,"size_download":249,"speed_download":494,"speed_upload":65,"download_content_length":-1,"upload_content_length":33,"starttransfer_time":0.183378,"redirect_time":0,"redirect_url":"","primary_ip":"18.140.166.245","certinfo":[],"primary_port":443,"local_ip":"103.226.249.222","local_port":34550},"params":{"method":"crm.product.list","params":{"filter":{"XML_ID":"SM-A135FZ0HXXV"}}},"result":{"result":[],"total":0,"time":{"start":1655783575.375607,"finish":1655783575.41612,"duration":0.040513038635253906,"processing":0.01736593246459961,"date_start":"2022-06-21T06:52:55+03:00","date_finish":"2022-06-21T06:52:55+03:00","operating":0}}}