{"url":"https:\/\/ddtm.bitrix24.vn\/rest\/37552\/ffio7v4s9hae8sgv\/crm.contact.list.json","info":{"url":"https:\/\/ddtm.bitrix24.vn\/rest\/37552\/ffio7v4s9hae8sgv\/crm.contact.list.json","content_type":"application\/json; charset=utf-8","http_code":200,"header_size":1096,"request_size":210,"filetime":-1,"ssl_verify_result":0,"redirect_count":0,"total_time":0.549038,"namelookup_time":0.079383,"connect_time":0.124604,"pretransfer_time":0.22577,"size_upload":352,"size_download":249,"speed_download":453,"speed_upload":641,"download_content_length":-1,"upload_content_length":352,"starttransfer_time":0.225836,"redirect_time":0,"redirect_url":"","primary_ip":"18.140.166.245","certinfo":[],"primary_port":443,"local_ip":"103.226.249.222","local_port":42276},"params":{"method":"crm.contact.list","params":{"filter":{"PHONE":"+84702565755"},"select":["ID","NAME","PHONE","EMAIL","ADDRESS","ADDRESS_CITY","ADDRESS_REGION","ADDRESS_PROVINCE","ADDRESS_COUNTRY","TYPE_ID","SOURCE_ID","ASSIGNED_BY_ID","MODIFY_BY_ID"]}},"result":{"result":[],"total":0,"time":{"start":1657171836.019557,"finish":1657171836.065137,"duration":0.04557991027832031,"processing":0.02466297149658203,"date_start":"2022-07-07T08:30:36+03:00","date_finish":"2022-07-07T08:30:36+03:00","operating":0}}}