{"url":"https:\/\/ddtm.bitrix24.vn\/rest\/37552\/ffio7v4s9hae8sgv\/crm.contact.update.json","info":{"url":"https:\/\/ddtm.bitrix24.vn\/rest\/37552\/ffio7v4s9hae8sgv\/crm.contact.update.json","content_type":"application\/json; charset=utf-8","http_code":200,"header_size":1097,"request_size":212,"filetime":-1,"ssl_verify_result":0,"redirect_count":0,"total_time":0.769899,"namelookup_time":0.111291,"connect_time":0.15677,"pretransfer_time":0.25672,"size_upload":593,"size_download":257,"speed_download":334,"speed_upload":771,"download_content_length":-1,"upload_content_length":593,"starttransfer_time":0.256777,"redirect_time":0,"redirect_url":"","primary_ip":"18.140.166.245","certinfo":[],"primary_port":443,"local_ip":"103.226.249.222","local_port":58242,"http_version":3,"protocol":2,"ssl_verifyresult":0,"scheme":"HTTPS","appconnect_time_us":256498,"connect_time_us":156770,"namelookup_time_us":111291,"pretransfer_time_us":256720,"redirect_time_us":0,"starttransfer_time_us":256777,"total_time_us":769899},"params":{"method":"crm.contact.update","params":{"id":"66062","fields":{"NAME":"Ho\u00e0ng H\u1eefu D\u0169ng","ADDRESS":"Khu d\u00e2n chi ng\u00e1i ph\u01b0\u1eddng c\u1ed9ng ho\u00e0 th\u00e0nh ph\u1ed1 ch\u00ed linh t\u1ec9nh H\u1ea3i D\u01b0\u01a1ng, C\u1ed9ng H\u00f2a, Ch\u00ed Linh, H\u1ea3i D\u01b0\u01a1ng","ADDRESS_CITY":"Ch\u00ed Linh","ADDRESS_REGION":"C\u1ed9ng H\u00f2a","ADDRESS_PROVINCE":"H\u1ea3i D\u01b0\u01a1ng","ADDRESS_COUNTRY":"Vi\u1ec7t Nam","EMAIL":[{"VALUE":"ddtmonline@gmail.com","VALUE_TYPE":"WORK"}]}}},"result":{"result":true,"time":{"start":1659155260.629576,"finish":1659155260.867078,"duration":0.2375020980834961,"processing":0.21636509895324707,"date_start":"2022-07-30T07:27:40+03:00","date_finish":"2022-07-30T07:27:40+03:00","operating":0.21634316444396973}}}